cloud_savegame/VERSION
cloud_savegame/__init__.py
cloud_savegame/rules/18-wheels-of-steel-haulin.txt
cloud_savegame/rules/18-wheels-of-steel-pedal-to-the-metal.txt
cloud_savegame/rules/american-truck-simulator.txt
cloud_savegame/rules/app-image-glass.txt
cloud_savegame/rules/app-speedtest-cli.txt
cloud_savegame/rules/baldurs-gate-3.txt
cloud_savegame/rules/bully-scholarship-edition.txt
cloud_savegame/rules/cyberpunk-2077.txt
cloud_savegame/rules/dead-space-2008.txt
cloud_savegame/rules/detroit-become-human.txt
cloud_savegame/rules/dirt-3.txt
cloud_savegame/rules/emulator-mesen.txt
cloud_savegame/rules/euro-truck-simulator-2.txt
cloud_savegame/rules/fallout-new-vegas.txt
cloud_savegame/rules/farming-simulator-19.txt
cloud_savegame/rules/farming-simulator-2013.txt
cloud_savegame/rules/flatout-2.txt
cloud_savegame/rules/goldberg-steam-emulator.txt
cloud_savegame/rules/grand-theft-auto-iv.txt
cloud_savegame/rules/grand-theft-auto-san-andreas.txt
cloud_savegame/rules/grand-theft-auto-v.txt
cloud_savegame/rules/grand-theft-auto-vice-city.txt
cloud_savegame/rules/hacknet.txt
cloud_savegame/rules/minecraft.txt
cloud_savegame/rules/need-for-speed-most-wanted-2005.txt
cloud_savegame/rules/need-for-speed-underground-2.txt
cloud_savegame/rules/poly-bridge.txt
cloud_savegame/rules/rimworld.txt
cloud_savegame/rules/scrap-mechanic.txt
cloud_savegame/rules/starfield.txt
cloud_savegame/rules/stray.txt
cloud_savegame/rules/super-tux-kart.txt
cloud_savegame/rules/the-binding-of-isaac-afterbirth.txt
cloud_savegame/rules/the-elder-scrolls-v-skyrim-special-edition.txt
cloud_savegame/rules/watch-dogs-2.txt
cloud_savegame-0.4.1.dist-info/METADATA
cloud_savegame-0.4.1.dist-info/WHEEL
cloud_savegame-0.4.1.dist-info/entry_points.txt
cloud_savegame-0.4.1.dist-info/licenses/LICENSE
cloud_savegame-0.4.1.dist-info/RECORD
