Metadata-Version: 2.4
Name: cloud-savegame
Version: 0.4.1
License-File: LICENSE
Provides-Extra: dev
Requires-Dist: pytest; extra == 'dev'
Requires-Dist: pytest-cov; extra == 'dev'
Requires-Dist: ruff; extra == 'dev'
